dora_qwen/__init__.py
dora_qwen/__main__.py
dora_qwen/main.py
dora_qwen-0.4.1.dist-info/METADATA
dora_qwen-0.4.1.dist-info/WHEEL
dora_qwen-0.4.1.dist-info/entry_points.txt
dora_qwen-0.4.1.dist-info/top_level.txt
dora_qwen-0.4.1.dist-info/RECORD
