Metadata-Version: 2.4
Name: dora-qwen
Version: 0.4.1
Summary: dora-qwen
Author-email: Your Name <email@email.com>
License: MIT
Requires-Python: >=3.9
Requires-Dist: dora-rs>=0.3.9
Requires-Dist: torch>=2.7.0
Requires-Dist: torchvision>=0.22
Requires-Dist: torchaudio>=2.7.0
Requires-Dist: opencv-python>=4.1.1
Requires-Dist: modelscope>=1.18.1
Requires-Dist: accelerate>=1.3.0
Requires-Dist: transformers<=4.52.1
Requires-Dist: mlx-lm>=0.21.1; sys_platform == "darwin"
Requires-Dist: llama-cpp-python
